setup.py
glamkit_smartlinks.egg-info/PKG-INFO
glamkit_smartlinks.egg-info/SOURCES.txt
glamkit_smartlinks.egg-info/dependency_links.txt
glamkit_smartlinks.egg-info/not-zip-safe
glamkit_smartlinks.egg-info/top_level.txt
smartlinks/__init__.py
smartlinks/models.py
smartlinks/search_types.py
smartlinks/shortcuts.py
smartlinks/utils.py
smartlinks/templatetags/__init__.py
smartlinks/templatetags/smartlinks.py
smartlinks/tests/__init__.py
smartlinks/tests/testapp/__init__.py
smartlinks/tests/testapp/admin.py
smartlinks/tests/testapp/models.py
smartlinks/tests/testapp/views.py